Sinal/sing.v
module sing(
      input [9:0] px,
      input [9:0] py,
      input selPonto,
      output LEDG
);

      reg [9:0] p1x;
      reg [9:0] p1y;
      reg [9:0] p2x;
      reg [9:0] p2y;
      reg [9:0] p3x;
      reg [9:0] p3y;
      reg [9:0] ptx;
      reg [9:0] pty;
      reg [2:0] state = 1'b0;
      wire [9:0] sing;
      wire [10:0] p1;
      wire [10:0] p2;
      wire [10:0] p3;
      wire [10:0] p4;

      assign p1 = p1x - p3x;
      assign p2 = p2y - p3y;
      assign p3 = p2x - p3x;
      assign p4 = p1y - p3y;
      assign sing = p1 * p2 - p3 * p4;

      always @(selPonto) begin
              if (state == 1'b0) begin
                      p1x <= px;
                      p1y <= py;
                      state <= 1'b1;
              end else if (state == 1'b1) begin
                      p2x <= px;
                      p2y <= py;
                      state <= 2'b10;
              end else if (state == 2'b10) begin
                      p3x <= px;
                      p3y <= py;
                      state <= 2'b11;
              end else if (state == 2'b11) begin
                      ptx <= px;
                      pty <= py;
                      state <= 3'b100;
              end else begin
                      state <= 1'b0;
              end
      end

endmodule


module test();
        reg [9:0] px;
        reg [9:0] py;
        reg selPonto;
        wire led;

        sing sinal(px, py, selPonto, led);

        initial begin
                $dumpvars(0, sinal);
                #2 selPonto = 0;
                #2
                px <= 2; py <= 2; selPonto = 1;
                #2 selPonto = 0;
                #2
                px <= 0; py <= 0; selPonto = 1;
                #2 selPonto = 0;
                #2
                px <= 4; py <= 0; selPonto = 1;
                #2 selPonto = 0;
                #2
                px <= 3; py <= 1; selPonto = 1;
        end
endmodule

Sinal/dump.vcd
$date
	Tue May  9 20:59:49 2017
$end
$version
	Icarus Verilog
$end
$timescale
	1s
$end
$scope module test $end
$scope module sinal $end
$var wire 1 ! LEDG $end
$var wire 10 " px [9:0] $end
$var wire 10 # py [9:0] $end
$var wire 1 $ selPonto $end
$var wire 10 % sing [9:0] $end
$var wire 11 & p4 [10:0] $end
$var wire 11 ' p3 [10:0] $end
$var wire 11 ( p2 [10:0] $end
$var wire 11 ) p1 [10:0] $end
$var reg 10 * p1x [9:0] $end
$var reg 10 + p1y [9:0] $end
$var reg 10 , p2x [9:0] $end
$var reg 10 - p2y [9:0] $end
$var reg 10 . p3x [9:0] $end
$var reg 10 / p3y [9:0] $end
$var reg 10 0 ptx [9:0] $end
$var reg 10 1 pty [9:0] $end
$var reg 3 2 state [2:0] $end
$upscope $end
$upscope $end
$enddefinitions $end
#0
$dumpvars
b0 2
bx 1
bx 0
bx /
bx .
bx -
bx ,
bx +
bx *
bx )
bx (
bx '
bx &
bx %
x$
bx #
bx "
z!
$end
#2
b1 2
0$
#4
b10 2
b10 #
b10 "
1$
#6
b11 2
b10 /
b10 .
0$
#8
b100 2
b10 1
b10 0
b0 #
b0 "
1$
#10
b0 2
0$
#12
b1 2
b11111111110 &
b0 +
b11111111110 )
b0 *
b100 "
1$
#14
b1000 %
b10 2
b11111111110 (
b0 -
b10 '
b100 ,
0$
#16
b0 %
b11 2
b0 (
b0 &
b0 /
b11111111100 )
b0 '
b100 .
b1 #
b11 "
1$
